blinter.py
blinter-1.0.112.dist-info/licenses/COPYING
blinter-1.0.112.dist-info/METADATA
blinter-1.0.112.dist-info/WHEEL
blinter-1.0.112.dist-info/entry_points.txt
blinter-1.0.112.dist-info/top_level.txt
blinter-1.0.112.dist-info/RECORD
