Metadata-Version: 2.4
Name: Blinter
Version: 1.0.112
Summary: Blinter is a linter for Windows batch files. It provides comprehensive static analysis to identify syntax errors, security vulnerabilities, performance issues and style problems.
Author-email: tboy1337 <tboy1337@proton.me>
Maintainer-email: tboy1337 <tboy1337@proton.me>
License-Expression: AGPL-3.0-or-later
Project-URL: Homepage, https://github.com/tboy1337/Blinter
Project-URL: Documentation, https://github.com/tboy1337/Blinter
Project-URL: Repository, https://github.com/tboy1337/Blinter.git
Project-URL: Issues, https://github.com/tboy1337/Blinter/issues
Keywords: lint,python,windows,analysis,script,linting,linter,static-analysis,static,batch,batch-file,cmd,batch-script,batchfile,bat,script-analysis
Classifier: Development Status :: 4 - Beta
Classifier: Intended Audience :: Developers
Classifier: Operating System :: Microsoft :: Windows
Classifier: Programming Language :: Python :: 3 :: Only
Classifier: Programming Language :: Python :: 3
Classifier: Programming Language :: Python :: 3.10
Classifier: Programming Language :: Python :: 3.11
Classifier: Programming Language :: Python :: 3.12
Classifier: Programming Language :: Python :: 3.13
Classifier: Programming Language :: Python :: 3.14
Classifier: Topic :: Software Development :: Quality Assurance
Classifier: Topic :: Software Development :: Code Generators
Classifier: Topic :: System :: Systems Administration
Classifier: Environment :: Console
Requires-Python: >=3.10
License-File: COPYING
Requires-Dist: charset_normalizer
Provides-Extra: dev
Requires-Dist: pytest; extra == "dev"
Requires-Dist: pytest-asyncio; extra == "dev"
Requires-Dist: pytest-timeout; extra == "dev"
Requires-Dist: pytest-xdist; extra == "dev"
Requires-Dist: pytest-mock; extra == "dev"
Requires-Dist: pytest-cov; extra == "dev"
Requires-Dist: hypothesis; extra == "dev"
Requires-Dist: pytest-html; extra == "dev"
Requires-Dist: pytest-json-report; extra == "dev"
Requires-Dist: pytest-benchmark; extra == "dev"
Requires-Dist: pytest-rerunfailures; extra == "dev"
Requires-Dist: pylint; extra == "dev"
Requires-Dist: mypy; extra == "dev"
Requires-Dist: autopep8; extra == "dev"
Requires-Dist: black; extra == "dev"
Requires-Dist: isort; extra == "dev"
Dynamic: license-file
